typest/__main__.py
typest/error.py
typest/outcomes/__init__.py
typest/outcomes/base.py
typest/outcomes/flaw.py
typest/outcomes/mismatch.py
typest/outcomes/revealed_type.py
typest/typecheckers/__init__.py
typest/typecheckers/base.py
typest/typecheckers/mypy.py
typest/typecheckers/pyright.py
typest/utils/color.py
typest/utils/fake_type.py
typest-0.3.2.dist-info/WHEEL
typest-0.3.2.dist-info/METADATA
typest-0.3.2.dist-info/RECORD
