Metadata-Version: 2.1
Name: typest
Version: 0.3.2
Summary: A framework for testing type expectations
Home-page: https://github.com/jonathan-scholbach/typest
License: MIT
Author: Jonathan Scholbach
Author-email: j.scholbach@posteo.de
Requires-Python: >=3.10,<4.0
Classifier: License :: OSI Approved :: MIT License
Classifier: Programming Language :: Python :: 3
Classifier: Programming Language :: Python :: 3.10
Classifier: Programming Language :: Python :: 3.11
Requires-Dist: comment-parser (>=1.2.4,<2.0.0)
Requires-Dist: mypy (>=0.991,<0.992)
Requires-Dist: pyright (>=1.1,<2.0)
Project-URL: Repository, https://github.com/jonathan-scholbach/typest
